src/__init__.py
src/__main__.py
src/alphabetize.py
alphabetize-0.0.15.dist-info/LICENSE
alphabetize-0.0.15.dist-info/METADATA
alphabetize-0.0.15.dist-info/WHEEL
alphabetize-0.0.15.dist-info/entry_points.txt
alphabetize-0.0.15.dist-info/top_level.txt
alphabetize-0.0.15.dist-info/RECORD
