Metadata-Version: 2.1
Name: alphabetize
Version: 0.0.15
Summary: Alphabetize variables within your files
Home-page: https://github.com/JakeAdey/alphabetize
Author: Jake Adey
Author-email: jakespenceradey@gmail.com
License: MIT
Keywords: alphabetise,alphabetize,ordering,sorting,variable sorting
Classifier: Development Status :: 5 - Production/Stable
Classifier: Intended Audience :: Developers
Classifier: License :: OSI Approved :: MIT License
Classifier: Operating System :: Microsoft :: Windows
Classifier: Programming Language :: Python
Classifier: Programming Language :: Python :: 3
Classifier: Programming Language :: Python :: 3 :: Only
Classifier: Programming Language :: Python :: 3.6
Classifier: Programming Language :: Python :: 3.7
Classifier: Programming Language :: Python :: 3.8
Classifier: Programming Language :: Python :: 3.9
Classifier: Programming Language :: Python :: 3.10
Classifier: Programming Language :: Python :: 3.11
Classifier: Programming Language :: Python :: Implementation :: CPython
Classifier: Programming Language :: Python :: Implementation :: PyPy
Classifier: Topic :: Software Development :: Quality Assurance
License-File: LICENSE
Requires-Dist: setuptools
Requires-Dist: wheel
